{"groups": {}, "interval": "1day", "assets": ["MOO", "VEGI", "FTAG", "IVEG", "KROP", "SPY", "SHY"], "strategy": [{"type": "IF", "conditions": [{"type": "BINARY", "first": {"name": "RSI", "args": {"length": "14", "ticker": "SPY"}, "advanced": {}}, "second": {"name": "constant", "args": {"value": "81"}}, "comp": ">", "operator": ""}], "if_action": {"type": "ACTION", "steps": [{"action": "allocation", "asset": "SHY", "amount": 100}]}, "else_action": {"type": "ACTION", "steps": [{"action": "allocation", "asset": "SPY", "amount": 100}]}}]}